scraped/__init__.py
scraped/tools.py
scraped/util.py
scraped-0.0.11.dist-info/LICENSE
scraped-0.0.11.dist-info/METADATA
scraped-0.0.11.dist-info/WHEEL
scraped-0.0.11.dist-info/entry_points.txt
scraped-0.0.11.dist-info/top_level.txt
scraped-0.0.11.dist-info/RECORD
