Metadata-Version: 2.1
Name: scraped
Version: 0.0.11
Summary: Tools for scraping
Home-page: https://github.com/thorwhalen/scraped
Author: Thor Whalen
License: mit
Platform: any
License-File: LICENSE
Requires-Dist: graze
Requires-Dist: scrapy
Requires-Dist: config2py
Requires-Dist: html2text
Requires-Dist: lkj
Requires-Dist: argh
